tfpyth/__init__.py
tfpyth-1.0.1.dist-info/LICENSE
tfpyth-1.0.1.dist-info/METADATA
tfpyth-1.0.1.dist-info/WHEEL
tfpyth-1.0.1.dist-info/top_level.txt
tfpyth-1.0.1.dist-info/RECORD
