Metadata-Version: 2.1
Name: tfpyth
Version: 1.0.1
Summary: Putting TensorFlow back in PyTorch, back in Tensorflow (differentiable TensorFlow PyTorch adapters).
Home-page: https://github.com/blackhc/tfpyth
Author: Andreas @blackhc Kirsch
Author-email: blackhc+tfpyth@gmail.com
License: MIT
Keywords: ml machine learning
Platform: UNKNOWN
Classifier: Development Status :: 4 - Beta
Classifier: Intended Audience :: Developers
Classifier: Intended Audience :: Science/Research
Classifier: Topic :: Software Development :: Libraries :: Python Modules
Classifier: License :: OSI Approved :: MIT License
Classifier: Programming Language :: Python :: 3.6
Requires-Dist: tensorflow (~=1.14)
Requires-Dist: torch (~=1.1)
Provides-Extra: dev
Requires-Dist: check-manifest ; extra == 'dev'
Provides-Extra: test
Requires-Dist: coverage ; extra == 'test'
Requires-Dist: codecov ; extra == 'test'
Requires-Dist: pytest ; extra == 'test'
Requires-Dist: pytest-cov ; extra == 'test'
